setup.py
vpp.c
vpp.py
vpp.egg-info/PKG-INFO
vpp.egg-info/SOURCES.txt
vpp.egg-info/dependency_links.txt
vpp.egg-info/top_level.txt