Metadata-Version: 1.1
Name: vpp
Version: 2.5.0.post2
Summary: Python wrapper to vpp
Home-page: https://github.com/kidanger/vpp
Author: Jérémy Anger
Author-email: angerj.dev@gmail.com
License: UNKNOWN
Platform: UNKNOWN
Classifier: Operating System :: OS Independent
